rqcrypt/__init__.py
rqcrypt/examples/__init__.py
rqcrypt/examples/example_scrngV2.py
rqcrypt/scrngV2/_utils.py
rqcrypt/scrngV2/scrngV2.py
rqcrypt-0.0.1.dist-info/METADATA
rqcrypt-0.0.1.dist-info/WHEEL
rqcrypt-0.0.1.dist-info/licenses/LICENSE.txt
rqcrypt-0.0.1.dist-info/RECORD
