Metadata-Version: 2.4
Name: rqcrypt
Version: 0.0.1
Summary: (Very simple) Quantum-powered cryptography
License-Expression: MIT
License-File: LICENSE.txt
Author: Rohan Date
Author-email: rohan.s.date@icloud.com
Requires-Python: >=3.14
Classifier: Development Status :: 3 - Alpha
Classifier: Intended Audience :: Science/Research
Classifier: Topic :: Scientific/Engineering :: Quantum Computing
Classifier: Topic :: Security :: Cryptography
Classifier: Programming Language :: Python :: 3
Classifier: Programming Language :: Python :: 3.14
Classifier: Programming Language :: Python :: 3.13
Classifier: Programming Language :: Python :: 3.12
Classifier: Programming Language :: Python :: 3.11
Requires-Dist: colorama (>=0.4.6,<0.5.0)
Requires-Dist: matplotlib (>=3.10.8,<4.0.0)
Requires-Dist: pylatexenc (>=2.10,<3.0)
Requires-Dist: pytest (>=9.0.2,<10.0.0)
Requires-Dist: qiskit (>=2.3.0,<3.0.0)
Requires-Dist: qiskit-ibm-runtime (>=0.45.0,<0.46.0)
Requires-Dist: tqdm (>=4.67.1,<5.0.0)
Requires-Dist: twine (>=6.2.0,<7.0.0)
Project-URL: Homepage, https://github.com/rsdate/ShadowCrypt
Project-URL: Issues, https://github.com/rsdate/ShadowCrypt/issues
